MessengerCounter.py
mc.py
messenger_counter-0.5.1.dist-info/METADATA
messenger_counter-0.5.1.dist-info/WHEEL
messenger_counter-0.5.1.dist-info/licenses/LICENSE
messenger_counter-0.5.1.dist-info/RECORD
