Metadata-Version: 2.1
Name: messenger-counter
Version: 0.5.1
Summary: Package for counting messages from Facebook Messenger
Project-URL: Code, https://github.com/KMChris/messenger-counter
Project-URL: Documentation, https://messenger-counter.mizgala.pl/
Project-URL: Download, https://pypi.org/project/messenger-counter/
Project-URL: Homepage, https://github.com/KMChris/messenger-counter
Project-URL: Issue Tracker, https://github.com/KMChris/messenger-counter/issues
Author-email: Krzysztof Mizgała <krzysztof@mizgala.pl>
License-Expression: MIT
License-File: LICENSE
Keywords: chart,count,counter,facebook,messages,messenger,statistics,stats
Classifier: Development Status :: 4 - Beta
Classifier: Environment :: Console
Classifier: Intended Audience :: Developers
Classifier: Intended Audience :: End Users/Desktop
Classifier: License :: OSI Approved :: MIT License
Classifier: Operating System :: OS Independent
Classifier: Programming Language :: Python :: 3
Classifier: Topic :: Scientific/Engineering :: Visualization
Requires-Python: >=3.6
Requires-Dist: matplotlib
Requires-Dist: pandas
